loutrinette/__init__.py
loutrinette/cli.py
loutrinette-0.0.1.dist-info/METADATA
loutrinette-0.0.1.dist-info/WHEEL
loutrinette-0.0.1.dist-info/entry_points.txt
loutrinette-0.0.1.dist-info/RECORD
